juno_magic/__init__.py
juno_magic/bridge.py
juno_magic/client.py
juno_magic/runner.py
juno_magic/extensions/__init__.py
juno_magic/extensions/wamp.py
juno_magic-0.2.3.data/data/share/jupyter/nbextensions/juno_magic/index.js
juno_magic-0.2.3.dist-info/DESCRIPTION.rst
juno_magic-0.2.3.dist-info/METADATA
juno_magic-0.2.3.dist-info/RECORD
juno_magic-0.2.3.dist-info/WHEEL
juno_magic-0.2.3.dist-info/entry_points.txt
juno_magic-0.2.3.dist-info/metadata.json
juno_magic-0.2.3.dist-info/top_level.txt
