Metadata-Version: 2.0
Name: juno-magic
Version: 0.2.3
Summary: IPython magics and utilities to work with bridged kernels
Home-page: https://github.com/timbr-io/juno-magic
Author: Pramukta Kumar
Author-email: pramukta.kumar@timbr.io
License: MIT
Platform: UNKNOWN
Requires-Dist: autobahn
Requires-Dist: ipython
Requires-Dist: pyopenssl
Requires-Dist: requests
Requires-Dist: service-identity
Requires-Dist: sh
Requires-Dist: twisted
Requires-Dist: txzmq
Requires-Dist: zope.interface
